uh_soundscapes/__init__.py
uh_soundscapes/astra_reader.py
uh_soundscapes/data_processing.py
uh_soundscapes/dataset_reader.py
uh_soundscapes/dataset_standardization.py
uh_soundscapes/esc50_reader.py
uh_soundscapes/orex_reader.py
uh_soundscapes/shared_explosions_reader.py
uh_soundscapes/standard_labels.py
uh_soundscapes/test_readers.py
uh_soundscapes-1.1.6.dist-info/licenses/LICENSE
uh_soundscapes-1.1.6.dist-info/METADATA
uh_soundscapes-1.1.6.dist-info/WHEEL
uh_soundscapes-1.1.6.dist-info/top_level.txt
uh_soundscapes-1.1.6.dist-info/RECORD
