Metadata-Version: 2.4
Name: uh_soundscapes
Version: 1.1.6
Summary: Read audio data for an event, process it, and create an exportable product.
Author: ISLA, UH
License-Expression: Apache-2.0
Project-URL: homepage, https://github.com/ISLA-UH/UH_Soundscapes
Requires-Python: >=3.9
License-File: LICENSE
Requires-Dist: fastkml>=1.1.0
Requires-Dist: ipykernel>=6.30.0
Requires-Dist: lxml>=6.0.1
Requires-Dist: pandas>=2.1.3
Requires-Dist: quantum-inferno>=1.1.3
Dynamic: license-file
